ekyc/.DS_Store
ekyc/__init__.py
ekyc/core.py
ekyc/document_verification.py
ekyc/face_matching.py
ekyc/face_processing.py
ekyc/liveness_check.py
ekyc/test.py
ekyc/utils.py
ekyc/data/ic_template.jpg
ekyc/data/shape_predictor_68_face_landmarks.dat
ekyc-0.1.15.dist-info/LICENSE
ekyc-0.1.15.dist-info/METADATA
ekyc-0.1.15.dist-info/WHEEL
ekyc-0.1.15.dist-info/top_level.txt
ekyc-0.1.15.dist-info/RECORD
