Metadata-Version: 2.1
Name: ekyc
Version: 0.1.15
Summary: A library for electronic Know Your Customer (eKYC) verification
Author-email: Prabhjeevan Singh <prabhjeevan@juarapartners.com>
License: MIT License
Project-URL: Homepage, https://github.com/juaraprabhjeevan/juara_ekyc
Project-URL: Bug Tracker, https://github.com/juaraprabhjeevan/juara_ekyc/issues
Keywords: eKYC,verification,identity
Classifier: Development Status :: 3 - Alpha
Classifier: Intended Audience :: Developers
Classifier: License :: OSI Approved :: MIT License
Classifier: Operating System :: OS Independent
Classifier: Programming Language :: Python :: 3
Classifier: Programming Language :: Python :: 3.9
Classifier: Programming Language :: Python :: 3.10
Classifier: Programming Language :: Python :: 3.11
Classifier: Programming Language :: Python :: 3.12
Requires-Python: <3.13,>=3.9
License-File: LICENSE
Requires-Dist: opencv-python
Requires-Dist: numpy
Requires-Dist: scikit-learn
Requires-Dist: deepface
Requires-Dist: Flask
Requires-Dist: paddlepaddle==2.6.1
Requires-Dist: paddleocr==2.8.1
Requires-Dist: tensorflow==2.11.0
Requires-Dist: protobuf==3.19.6
Requires-Dist: dlib>=19.22.0; platform_system != "Windows"
Provides-Extra: dev
Requires-Dist: pytest; extra == "dev"
Requires-Dist: flake8; extra == "dev"
